{
  "project_info": {
    "project_number": "457124736555",
    "project_id": "firbase-auth-bloc",
    "storage_bucket": "firbase-auth-bloc.appspot.com"
  },
  "client": [
    {
      "client_info": {
        "mobilesdk_app_id": "1:457124736555:android:88572c87ccde969269846e",
        "android_client_info": {
          "package_name": "com.example.firebase_auth_app_bloc"
        }
      },
      "oauth_client": [],
      "api_key": [
        {
          "current_key": "AIzaSyA5euPqd1Oz14YBVVUrnaX8sNBLwDk3UkQ"
        }
      ],
      "services": {
        "appinvite_service": {
          "other_platform_oauth_client": []
        }
      }
    }
  ],
  "configuration_version": "1"
}